tf_keras/__init__.py
tf_keras/__internal__/__init__.py
tf_keras/__internal__/backend/__init__.py
tf_keras/__internal__/layers/__init__.py
tf_keras/__internal__/losses/__init__.py
tf_keras/__internal__/models/__init__.py
tf_keras/__internal__/optimizers/__init__.py
tf_keras/__internal__/utils/__init__.py
tf_keras/activations/__init__.py
tf_keras/api/__init__.py
tf_keras/api/_v1/__init__.py
tf_keras/api/_v1/keras/__init__.py
tf_keras/api/_v1/keras/__internal__/__init__.py
tf_keras/api/_v1/keras/__internal__/layers/__init__.py
tf_keras/api/_v1/keras/__internal__/legacy/__init__.py
tf_keras/api/_v1/keras/__internal__/legacy/layers/__init__.py
tf_keras/api/_v1/keras/__internal__/legacy/layers/experimental/__init__.py
tf_keras/api/_v1/keras/__internal__/legacy/rnn_cell/__init__.py
tf_keras/api/_v1/keras/activations/__init__.py
tf_keras/api/_v1/keras/applications/__init__.py
tf_keras/api/_v1/keras/applications/convnext/__init__.py
tf_keras/api/_v1/keras/applications/densenet/__init__.py
tf_keras/api/_v1/keras/applications/efficientnet/__init__.py
tf_keras/api/_v1/keras/applications/efficientnet_v2/__init__.py
tf_keras/api/_v1/keras/applications/imagenet_utils/__init__.py
tf_keras/api/_v1/keras/applications/inception_resnet_v2/__init__.py
tf_keras/api/_v1/keras/applications/inception_v3/__init__.py
tf_keras/api/_v1/keras/applications/mobilenet/__init__.py
tf_keras/api/_v1/keras/applications/mobilenet_v2/__init__.py
tf_keras/api/_v1/keras/applications/mobilenet_v3/__init__.py
tf_keras/api/_v1/keras/applications/nasnet/__init__.py
tf_keras/api/_v1/keras/applications/regnet/__init__.py
tf_keras/api/_v1/keras/applications/resnet/__init__.py
tf_keras/api/_v1/keras/applications/resnet50/__init__.py
tf_keras/api/_v1/keras/applications/resnet_rs/__init__.py
tf_keras/api/_v1/keras/applications/resnet_v2/__init__.py
tf_keras/api/_v1/keras/applications/vgg16/__init__.py
tf_keras/api/_v1/keras/applications/vgg19/__init__.py
tf_keras/api/_v1/keras/applications/xception/__init__.py
tf_keras-2.20.0.dist-info/METADATA
tf_keras-2.20.0.dist-info/WHEEL
tf_keras-2.20.0.dist-info/top_level.txt
tf_keras-2.20.0.dist-info/RECORD
